yt5/__init__.py
yt5/__main__.py
yt5/yt5.py
yt5-1.5.3.dist-info/LICENSE
yt5-1.5.3.dist-info/METADATA
yt5-1.5.3.dist-info/WHEEL
yt5-1.5.3.dist-info/entry_points.txt
yt5-1.5.3.dist-info/top_level.txt
yt5-1.5.3.dist-info/RECORD
