Metadata-Version: 2.1
Name: yt5
Version: 1.5.3
Summary: Download YouTube Videos and Audios
Home-page: https://github.com/Simatwa/yt5
Author: Smartwa Caleb
Author-email: smartwacaleb@gmail.com
Maintainer: Smartwa Caleb
License: MIT
Project-URL: Bug Report, https://github.com/Simatwa/yt5/issues/new
Keywords: yt5,youtubedl,youtube,downloader,video-downloader
Classifier: License :: OSI Approved :: MIT License
Classifier: Development Status :: 4 - Beta
Classifier: Intended Audience :: Developers
Classifier: Natural Language :: English
Classifier: License :: Free For Home Use
Classifier: Topic :: Home Automation
Classifier: Intended Audience :: Customer Service
Classifier: Programming Language :: Python
Classifier: Topic :: Software Development :: Libraries :: Python Modules
Classifier: Programming Language :: Python :: 3 :: Only
Classifier: Programming Language :: Python :: 3.8
Classifier: Programming Language :: Python :: 3.9
Classifier: Programming Language :: Python :: 3.10
Classifier: Programming Language :: Python :: 3.11
Requires-Python: >=3.8
License-File: LICENSE
Requires-Dist: colorama (==0.4.6)
Requires-Dist: pytube (==12.1.2)
Requires-Dist: tabulate (==0.9.0)
